{"nodes": [{"id": "d_hackathon_sentient_retention_engine_agentic_ai_tools_create_ticket_py", "label": "create_ticket.py", "file_type": "code", "source_file": "D:\\Hackathon\\Sentient-Retention Engine\\agentic-ai\\tools\\create_ticket.py", "source_location": "L1"}, {"id": "tools_create_ticket_rationale_1", "label": "# TODO: Implement tools/create_ticket.py logic", "file_type": "rationale", "source_file": "D:\\Hackathon\\Sentient-Retention Engine\\agentic-ai\\tools\\create_ticket.py", "source_location": "L1"}], "edges": [{"source": "tools_create_ticket_rationale_1", "target": "d_hackathon_sentient_retention_engine_agentic_ai_tools_create_ticket_py", "relation": "rationale_for", "confidence": "EXTRACTED", "source_file": "D:\\Hackathon\\Sentient-Retention Engine\\agentic-ai\\tools\\create_ticket.py", "source_location": "L1", "weight": 1.0}], "raw_calls": []}